flask_flywheel/__init__.py
flask_flywheel-0.1.0.dist-info/DESCRIPTION.rst
flask_flywheel-0.1.0.dist-info/METADATA
flask_flywheel-0.1.0.dist-info/RECORD
flask_flywheel-0.1.0.dist-info/WHEEL
flask_flywheel-0.1.0.dist-info/metadata.json
flask_flywheel-0.1.0.dist-info/pbr.json
flask_flywheel-0.1.0.dist-info/top_level.txt
