Metadata-Version: 2.0
Name: flask-flywheel
Version: 0.1.0
Summary: Adds Flywheel support to your Flask application
Home-page: http://github.com/iromli/flask-flywheel
Author: Isman Firmansyah
Author-email: isman.firmansyah@gmail.com
License: MIT
Platform: UNKNOWN
Classifier: Environment :: Web Environment
Classifier: Intended Audience :: Developers
Classifier: License :: OSI Approved :: MIT License
Classifier: Topic :: Internet :: WWW/HTTP :: Dynamic Content
Classifier: Topic :: Software Development :: Libraries :: Python Modules
Classifier: Programming Language :: Python
Classifier: Programming Language :: Python :: 2
Classifier: Programming Language :: Python :: 2.7
Classifier: Programming Language :: Python :: 3
Classifier: Programming Language :: Python :: 3.4
Requires-Dist: flask
Requires-Dist: flywheel
